CHANGES.rst
MANIFEST.in
README.rst
setup.py
metalchemy/__init__.py
metalchemy/metadata.py
metalchemy/types.py
metalchemy.egg-info/PKG-INFO
metalchemy.egg-info/SOURCES.txt
metalchemy.egg-info/dependency_links.txt
metalchemy.egg-info/requires.txt
metalchemy.egg-info/top_level.txt