Metadata-Version: 1.0
Name: metalchemy
Version: 1.0.0
Summary: SQLAlchemy hierarchical key/value helper
Home-page: https://github.com/paylogic/metalchemy
Author: Paylogic International
Author-email: developers@paylogic.com
License: MIT
Keywords: sqlalchemy dynamic object fields metadata key/value
Platform: UNKNOWN
